{"stats":{"minecraft:killed":{"minecraft:spider":7,"minecraft:phantom":7,"minecraft:skeleton":13,"minecraft:bee":2,"minecraft:chicken":23,"minecraft:husk":14,"minecraft:pig":1,"minecraft:salmon":1,"minecraft:rabbit":5,"minecraft:creeper":6,"minecraft:sheep":4,"minecraft:zombie":13,"minecraft:cow":1},"minecraft:picked_up":{"minecraft:wooden_axe":2,"minecraft:crafting_table":2,"minecraft:iron_chestplate":1,"minecraft:birch_door":7,"minecraft:wheat":2,"minecraft:chicken":23,"minecraft:wooden_pickaxe":1,"minecraft:oak_stairs":31,"minecraft:string":6,"minecraft:wooden_sword":3,"minecraft:iron_shovel":1,"minecraft:birch_fence":3,"minecraft:oak_sign":3,"minecraft:red_sand":72,"minecraft:detector_rail":1,"minecraft:beef":3,"minecraft:melon_slice":7,"minecraft:poppy":5,"minecraft:iron_pickaxe":1,"minecraft:sugar_cane":39,"minecraft:chest":3,"minecraft:phantom_membrane":2,"minecraft:egg":6,"minecraft:white_glazed_terracotta":1,"minecraft:stick":96,"minecraft:sandstone":456,"minecraft:oak_door":8,"minecraft:oak_fence":108,"minecraft:torch":122,"minecraft:porkchop":2,"minecraft:diorite":53,"minecraft:carrot":2,"minecraft:redstone":114,"minecraft:arrow":19,"minecraft:cactus":20,"minecraft:rotten_flesh":52,"minecraft:sandstone_stairs":7,"minecraft:gold_ingot":10,"minecraft:white_terracotta":103,"minecraft:mutton":8,"minecraft:rail":122,"minecraft:white_wool":3,"minecraft:cobblestone":628,"minecraft:oxeye_daisy":4,"minecraft:birch_log":111,"minecraft:feather":24,"minecraft:andesite":114,"minecraft:birch_slab":4,"minecraft:salmon":1,"minecraft:golden_leggings":1,"minecraft:birch_planks":39,"minecraft:flint":12,"minecraft:oak_log":349,"minecraft:gunpowder":8,"minecraft:lapis_lazuli":84,"minecraft:dirt":67,"minecraft:orange_terracotta":190,"minecraft:bone":18,"minecraft:apple":2,"minecraft:kelp":7,"minecraft:bow":3,"minecraft:wheat_seeds":42,"minecraft:light_gray_glazed_terracotta":14,"minecraft:stone_pickaxe":3,"minecraft:rabbit_hide":19,"minecraft:oak_fence_gate":4,"minecraft:iron_ore":212,"minecraft:rabbit":5,"minecraft:oak_planks":68,"minecraft:pumpkin":1,"minecraft:cooked_porkchop":2,"minecraft:dandelion":2,"minecraft:gravel":101,"minecraft:sand":1250,"minecraft:white_bed":3,"minecraft:gold_ore":20,"minecraft:red_terracotta":3,"minecraft:spider_eye":4,"minecraft:light_gray_terracotta":4,"minecraft:blue_terracotta":1,"minecraft:stone_axe":3,"minecraft:iron_helmet":1,"minecraft:granite":11,"minecraft:gray_wool":1,"minecraft:emerald":1,"minecraft:terracotta":434,"minecraft:oak_sapling":21,"minecraft:coal":167},"minecraft:custom":{"minecraft:mob_kills":97,"minecraft:animals_bred":13,"minecraft:interact_with_crafting_table":102,"minecraft:eat_cake_slice":1,"minecraft:leave_game":13,"minecraft:time_since_death":542896,"minecraft:climb_one_cm":424,"minecraft:sprint_one_cm":777660,"minecraft:walk_one_cm":2028775,"minecraft:drop":36,"minecraft:talked_to_villager":1,"minecraft:deaths":3,"minecraft:sneak_time":121,"minecraft:walk_under_water_one_cm":34580,"minecraft:jump":2233,"minecraft:walk_on_water_one_cm":62706,"minecraft:interact_with_furnace":88,"minecraft:play_one_minute":997760,"minecraft:sleep_in_bed":6,"minecraft:time_since_rest":270092,"minecraft:damage_taken":3398,"minecraft:minecart_one_cm":71774,"minecraft:damage_dealt":12828,"minecraft:fly_one_cm":82313,"minecraft:open_chest":93,"minecraft:crouch_one_cm":463,"minecraft:fall_one_cm":47486,"minecraft:horse_one_cm":229},"minecraft:dropped":{"minecraft:birch_planks":17,"minecraft:lapis_lazuli":15,"minecraft:oak_log":13,"minecraft:oak_fence":1,"minecraft:cobblestone":21,"minecraft:granite":1,"minecraft:birch_slab":3,"minecraft:torch":5,"minecraft:sand":70,"minecraft:cactus":4,"minecraft:birch_log":23,"minecraft:oak_door":2,"minecraft:dandelion":2,"minecraft:bone":5,"minecraft:stone_axe":1,"minecraft:sugar_cane":13,"minecraft:kelp":1,"minecraft:chicken":1,"minecraft:rotten_flesh":14,"minecraft:oak_sign":2,"minecraft:red_terracotta":1,"minecraft:rabbit_hide":4,"minecraft:gunpowder":2,"minecraft:andesite":7,"minecraft:birch_door":1,"minecraft:sandstone":19,"minecraft:red_sand":19,"minecraft:stone_pickaxe":1,"minecraft:bow":2},"minecraft:used":{"minecraft:oak_fence":243,"minecraft:blue_terracotta":22,"minecraft:red_sand":1,"minecraft:iron_shovel":704,"minecraft:stone_shovel":131,"minecraft:oak_sign":3,"minecraft:chest":9,"minecraft:white_terracotta":32,"minecraft:wooden_shovel":59,"minecraft:cooked_salmon":1,"minecraft:cooked_chicken":12,"minecraft:rotten_flesh":9,"minecraft:oak_door":1,"minecraft:torch":321,"minecraft:dirt":22,"minecraft:carrot":2,"minecraft:light_gray_glazed_terracotta":14,"minecraft:oak_fence_gate":6,"minecraft:birch_door":9,"minecraft:wooden_axe":56,"minecraft:iron_axe":800,"minecraft:oak_stairs":8,"minecraft:bow":37,"minecraft:furnace":3,"minecraft:minecart":1,"minecraft:egg":6,"minecraft:cooked_beef":3,"minecraft:orange_terracotta":119,"minecraft:wheat_seeds":2,"minecraft:cooked_mutton":6,"minecraft:sandstone_stairs":18,"minecraft:birch_planks":24,"minecraft:powered_rail":6,"minecraft:stone_pickaxe":213,"minecraft:oak_planks":554,"minecraft:wooden_pickaxe":116,"minecraft:sandstone":361,"minecraft:rail":290,"minecraft:sand":200,"minecraft:terracotta":287,"minecraft:crafting_table":6,"minecraft:light_gray_terracotta":8,"minecraft:white_bed":4,"minecraft:birch_fence":24,"minecraft:redstone_torch":3,"minecraft:apple":2,"minecraft:chicken":1,"minecraft:birch_slab":4,"minecraft:bread":18,"minecraft:iron_pickaxe":2122,"minecraft:white_glazed_terracotta":1,"minecraft:red_terracotta":33,"minecraft:oak_pressure_plate":4,"minecraft:stone_axe":365,"minecraft:wooden_sword":17,"minecraft:cobblestone":49,"minecraft:cooked_porkchop":2,"minecraft:cooked_rabbit":4,"minecraft:andesite":6,"minecraft:glass_pane":48},"minecraft:broken":{"minecraft:iron_shovel":2,"minecraft:wooden_shovel":1,"minecraft:wooden_pickaxe":2,"minecraft:stone_pickaxe":1,"minecraft:iron_axe":3,"minecraft:stone_axe":2,"minecraft:iron_pickaxe":8,"minecraft:wooden_axe":1,"minecraft:bow":1,"minecraft:stone_shovel":1},"minecraft:mined":{"minecraft:white_bed":3,"minecraft:oak_sapling":1,"minecraft:granite":9,"minecraft:red_sand":35,"minecraft:grass_block":46,"minecraft:birch_slab":4,"minecraft:kelp":3,"minecraft:oxeye_daisy":6,"minecraft:sandstone":253,"minecraft:sandstone_stairs":4,"minecraft:redstone_ore":14,"minecraft:iron_ore":187,"minecraft:andesite":91,"minecraft:pumpkin":1,"minecraft:white_glazed_terracotta":1,"minecraft:oak_sign":1,"minecraft:rail":127,"minecraft:stone":547,"minecraft:glass_pane":16,"minecraft:kelp_plant":2,"minecraft:orange_terracotta":200,"minecraft:dandelion":1,"minecraft:oak_fence":109,"minecraft:crafting_table":1,"minecraft:torch":21,"minecraft:light_gray_terracotta":8,"minecraft:melon":1,"minecraft:poppy":5,"minecraft:chest":3,"minecraft:dead_bush":54,"minecraft:cobblestone":10,"minecraft:lapis_ore":4,"minecraft:oak_planks":55,"minecraft:sugar_cane":4,"minecraft:diorite":53,"minecraft:wall_torch":61,"minecraft:white_terracotta":124,"minecraft:birch_planks":2,"minecraft:cactus":4,"minecraft:red_terracotta":2,"minecraft:light_gray_glazed_terracotta":14,"minecraft:blue_terracotta":1,"minecraft:birch_log":65,"minecraft:wheat":2,"minecraft:birch_leaves":2,"minecraft:bee_nest":1,"minecraft:grass":303,"minecraft:oak_log":347,"minecraft:coal_ore":129,"minecraft:oak_fence_gate":4,"minecraft:gravel":114,"minecraft:sand":935,"minecraft:dirt":30,"minecraft:brown_terracotta":28,"minecraft:terracotta":463,"minecraft:gold_ore":17,"minecraft:oak_leaves":78,"minecraft:birch_fence":3},"minecraft:crafted":{"minecraft:wooden_sword":1,"minecraft:oak_door":3,"minecraft:oak_planks":1048,"minecraft:stone_shovel":1,"minecraft:oak_sign":3,"minecraft:oak_pressure_plate":4,"minecraft:cooked_chicken":20,"minecraft:birch_slab":6,"minecraft:furnace":3,"minecraft:red_terracotta":32,"minecraft:cooked_mutton":8,"minecraft:glass_pane":64,"minecraft:glass":128,"minecraft:bow":1,"minecraft:iron_boots":1,"minecraft:white_glazed_terracotta":4,"minecraft:iron_axe":4,"minecraft:stone_pickaxe":3,"minecraft:chest":6,"minecraft:birch_door":6,"minecraft:rail":224,"minecraft:oak_fence":150,"minecraft:cooked_rabbit":4,"minecraft:minecart":1,"minecraft:cooked_beef":3,"minecraft:red_dye":5,"minecraft:light_gray_terracotta":8,"minecraft:wooden_shovel":1,"minecraft:arrow":48,"minecraft:cooked_porkchop":2,"minecraft:crafting_table":5,"minecraft:powered_rail":6,"minecraft:wooden_pickaxe":2,"minecraft:iron_helmet":1,"minecraft:cooked_salmon":1,"minecraft:birch_planks":124,"minecraft:stone_axe":3,"minecraft:air":0,"minecraft:blue_dye":12,"minecraft:oak_fence_gate":4,"minecraft:iron_chestplate":1,"minecraft:charcoal":17,"minecraft:birch_fence":21,"minecraft:stick":252,"minecraft:iron_ingot":155,"minecraft:iron_pickaxe":9,"minecraft:oak_stairs":68,"minecraft:wooden_axe":1,"minecraft:iron_shovel":3,"minecraft:gold_ingot":10,"minecraft:iron_leggings":1,"minecraft:sandstone":99,"minecraft:light_gray_dye":4,"minecraft:white_bed":1,"minecraft:redstone_torch":21,"minecraft:light_gray_glazed_terracotta":4,"minecraft:torch":248,"minecraft:blue_terracotta":32,"minecraft:sandstone_stairs":16,"minecraft:orange_glazed_terracotta":9},"minecraft:killed_by":{"minecraft:skeleton":2}},"DataVersion":2230}